ironoc_pytest_conor_heffron-2.3.0.dist-info/licenses/LICENSE.txt
ironoc_pytest_conorheffron/__init__.py
ironoc_pytest_conorheffron/github_api.py
ironoc_pytest_conorheffron/github_model.py
ironoc_pytest_conorheffron/tests/__init__.py
ironoc_pytest_conorheffron/tests/test_github_api.py
ironoc_pytest_conor_heffron-2.3.0.dist-info/METADATA
ironoc_pytest_conor_heffron-2.3.0.dist-info/WHEEL
ironoc_pytest_conor_heffron-2.3.0.dist-info/top_level.txt
ironoc_pytest_conor_heffron-2.3.0.dist-info/RECORD
