Metadata-Version: 2.4
Name: ironoc_pytest_conor_heffron
Version: 2.3.0
Summary: A pytest example package
Author-email: Conor Heffron <conor.heffron@gmail.com>
License: Copyright (c) 2016 The Python Packaging Authority (PyPA)
Project-URL: Homepage, https://github.com/conorheffron/ironoc-pytest
Project-URL: Issues, https://github.com/conorheffron/ironoc-pytest/issues
Classifier: Development Status :: 3 - Alpha
Classifier: Intended Audience :: Developers
Classifier: Topic :: Software Development :: Build Tools
Classifier: License :: OSI Approved :: MIT License
Classifier: Programming Language :: Python :: 3.14
Requires-Python: >=3.14
License-File: LICENSE.txt
Requires-Dist: argcomplete==3.6.3
Requires-Dist: attrs==25.4.0
Requires-Dist: certifi==2026.1.4
Requires-Dist: charset-normalizer==3.4.4
Requires-Dist: colorlog==6.10.1
Requires-Dist: dependency-groups==1.3.1
Requires-Dist: distlib==0.4.0
Requires-Dist: filelock==3.20.3
Requires-Dist: humanize==4.15.0
Requires-Dist: idna==3.11
Requires-Dist: iniconfig==2.3.0
Requires-Dist: nox==2025.11.12
Requires-Dist: numpy==2.4.1
Requires-Dist: packaging==26.0
Requires-Dist: pandas==3.0.0
Requires-Dist: platformdirs==4.5.1
Requires-Dist: pluggy==1.6.0
Requires-Dist: Pygments==2.19.2
Requires-Dist: pytest==9.0.2
Requires-Dist: python-dateutil==2.9.0.post0
Requires-Dist: pytz==2025.2
Requires-Dist: requests==2.32.5
Requires-Dist: setuptools==80.10.2
Requires-Dist: six==1.17.0
Requires-Dist: tzdata==2025.3
Requires-Dist: urllib3==2.6.3
Requires-Dist: virtualenv==20.36.1
Dynamic: license-file
